MANIFEST.in
README.md
requirements.txt
setup.py
cdtec/__init__.py
cdtec/base.py
cdtec/main.py
cdtec/utils.py
cdtec.egg-info/PKG-INFO
cdtec.egg-info/SOURCES.txt
cdtec.egg-info/dependency_links.txt
cdtec.egg-info/not-zip-safe
cdtec.egg-info/requires.txt
cdtec.egg-info/top_level.txt