Metadata-Version: 2.1
Name: cdtec
Version: 0.1.2
Summary: Change detection in satellite images
Home-page: https://framagit.org/benjaminpillot/change_detection
Author: Benjamin Pillot <benjamin.pillot@ird.fr>,  Bertrand Ygorra <bertrand.ygorra@inrae.fr>, Frédéric Frappart <frederic.frappart@legos.obs-mip.fr>, Thibault Catry <thibault.catry@ird.fr>
Author-email: benjaminpillot@riseup.net
License: MIT
Platform: UNKNOWN
Requires-Python: >=3
